{"area": "Jalan Pantai", "saved": "2026-06-11T12:27:56.896577", "rows": [{"Title": "Room \u00b7 Jalan Pantai, Port Dickson", "Property / Area": "Jalan Pantai, Port Dickson", "Room Type": "Room", "Bedrooms": 1, "Bathrooms": 1, "Price / month (RM)": 900.0, "Price / year (RM)": 10800.0, "Size (sqft)": null, "Furnishing": "Unfurnished", "Rent Type": "Monthly", "Min Duration (months)": 6, "Link": "https://speedhome.com/details/234roombed-ypapjcku"}, {"Title": "Room \u00b7 Jalan Pantai, Port Dickson", "Property / Area": "Jalan Pantai, Port Dickson", "Room Type": "Room", "Bedrooms": 1, "Bathrooms": 1, "Price / month (RM)": 900.0, "Price / year (RM)": 10800.0, "Size (sqft)": null, "Furnishing": "Unfurnished", "Rent Type": "Monthly", "Min Duration (months)": 6, "Link": "https://speedhome.com/details/roombed-qyghaenn"}, {"Title": "4BR \u00b7 PD Marina Terrace, Teluk Kemang", "Property / Area": "PD Marina Terrace, Teluk Kemang", "Room Type": "4BR", "Bedrooms": 4, "Bathrooms": 3, "Price / month (RM)": 3800.0, "Price / year (RM)": 45600.0, "Size (sqft)": 1800, "Furnishing": "Partially Furnished", "Rent Type": "Monthly", "Min Duration (months)": 12, "Link": "https://speedhome.com/details/marina-terrace-landed-house-bwoxmqis"}, {"Title": "Room \u00b7 Jalan Pantai, Port Dickson", "Property / Area": "Jalan Pantai, Port Dickson", "Room Type": "Room", "Bedrooms": 1, "Bathrooms": 1, "Price / month (RM)": 300.0, "Price / year (RM)": 3600.0, "Size (sqft)": null, "Furnishing": "Unfurnished", "Rent Type": "Monthly", "Min Duration (months)": 12, "Link": "https://speedhome.com/details/shop-lot-ygcbxscv"}]}