{"area": "Pinnacle Tower Apartment", "saved": "2026-06-11T12:48:08.115679", "rows": [{"Title": "Room \u00b7 SKS Habitat, Johor Bahru", "Property / Area": "SKS Habitat, Johor Bahru", "Room Type": "Room", "Bedrooms": 1, "Bathrooms": 1, "Price / month (RM)": 850.0, "Price / year (RM)": 10200.0, "Size (sqft)": null, "Furnishing": "Fully Furnished", "Rent Type": "Monthly", "Min Duration (months)": 6, "Link": "https://speedhome.com/details/sks-habitat-johor-bahru-ikqqiavb"}, {"Title": "2BR \u00b7 Trellis Residences, Johor Bahru", "Property / Area": "Trellis Residences, Johor Bahru", "Room Type": "2BR", "Bedrooms": 2, "Bathrooms": 1, "Price / month (RM)": 2500.0, "Price / year (RM)": 30000.0, "Size (sqft)": 650, "Furnishing": "Partially Furnished", "Rent Type": "Monthly", "Min Duration (months)": 12, "Link": "https://speedhome.com/details/the-threllis-tkkmjnip"}, {"Title": "2BR \u00b7 V SummerPlace, Johor Bahru", "Property / Area": "V SummerPlace, Johor Bahru", "Room Type": "2BR", "Bedrooms": 2, "Bathrooms": 2, "Price / month (RM)": 2600.0, "Price / year (RM)": 31200.0, "Size (sqft)": 650, "Furnishing": "Fully Furnished", "Rent Type": "Monthly", "Min Duration (months)": 12, "Link": "https://speedhome.com/details/v-summerplace-johor-bahru-yurxoprl"}, {"Title": "Room \u00b7 Pinnacle Tower Apartment, Johor Baru", "Property / Area": "Pinnacle Tower Apartment, Johor Baru", "Room Type": "Room", "Bedrooms": 1, "Bathrooms": 1, "Price / month (RM)": 750.0, "Price / year (RM)": 9000.0, "Size (sqft)": null, "Furnishing": "Partially Furnished", "Rent Type": "Monthly", "Min Duration (months)": 12, "Link": "https://speedhome.com/details/pinnacle-tower-apartment-johor-baru-kkfpzrqo"}, {"Title": "Room \u00b7 Pinnacle Tower Apartment, Johor Baru", "Property / Area": "Pinnacle Tower Apartment, Johor Baru", "Room Type": "Room", "Bedrooms": 1, "Bathrooms": 1, "Price / month (RM)": 1400.0, "Price / year (RM)": 16800.0, "Size (sqft)": null, "Furnishing": "Partially Furnished", "Rent Type": "Monthly", "Min Duration (months)": 12, "Link": "https://speedhome.com/details/pinnacle-tower-apartment-johor-baru-cryvsqqe"}]}