{"area": "Amara Residences, Batu Caves", "saved": "2026-06-10T14:06:13.518402", "rows": [{"Title": "Bennington Residences, Setapak", "Property / Area": "Bennington Residences, Setapak", "Room Type": "3BR", "Bedrooms": 3, "Bathrooms": 2, "Price / month (RM)": 1800.0, "Price / year (RM)": 21600.0, "Size (sqft)": 1236, "Furnishing": "Partially Furnished", "Rent Type": "Monthly", "Min Duration (months)": 12, "Link": "https://speedhome.com/details/bennington-residences-setapak-cdnhlmyj"}, {"Title": "Langat Jaya Condominium, Cheras", "Property / Area": "Langat Jaya Condominium, Cheras", "Room Type": "3BR", "Bedrooms": 3, "Bathrooms": 2, "Price / month (RM)": 1200.0, "Price / year (RM)": 14400.0, "Size (sqft)": 1000, "Furnishing": "Partially Furnished", "Rent Type": "Monthly", "Min Duration (months)": 12, "Link": "https://speedhome.com/details/langat-jaya-condominium-cheras-oggvgeis"}, {"Title": "Maya Bay Residence", "Property / Area": "Maya Bay Residence", "Room Type": "3BR", "Bedrooms": 3, "Bathrooms": 2, "Price / month (RM)": 1850.0, "Price / year (RM)": 22200.0, "Size (sqft)": 818, "Furnishing": "Partially Furnished", "Rent Type": "Monthly", "Min Duration (months)": 12, "Link": "https://speedhome.com/details/maya-bay-residence-jydgwfpc"}, {"Title": "Seni Residences, Sepang, Sunsuria City", "Property / Area": "Seni Residences, Sepang, Sunsuria City", "Room Type": "4BR", "Bedrooms": 4, "Bathrooms": 4, "Price / month (RM)": 4400.0, "Price / year (RM)": 52800.0, "Size (sqft)": 2578, "Furnishing": "Fully Furnished", "Rent Type": "Monthly", "Min Duration (months)": 12, "Link": "https://speedhome.com/details/seni-residences-sepang-sunsuria-city-xetkkond"}, {"Title": "Meta Residences, Seri Kembangan", "Property / Area": "Meta Residences, Seri Kembangan", "Room Type": "Room", "Bedrooms": 1, "Bathrooms": 1, "Price / month (RM)": 750.0, "Price / year (RM)": 9000.0, "Size (sqft)": 150, "Furnishing": "Fully Furnished", "Rent Type": "Monthly", "Min Duration (months)": 12, "Link": "https://speedhome.com/details/meta-residences-seri-kembangan-klxkntlm"}, {"Title": "Casa Residences", "Property / Area": "Casa Residences", "Room Type": "3BR", "Bedrooms": 3, "Bathrooms": 2, "Price / month (RM)": 1000.0, "Price / year (RM)": 12000.0, "Size (sqft)": 850, "Furnishing": "Unfurnished", "Rent Type": "Monthly", "Min Duration (months)": 12, "Link": "https://speedhome.com/details/casa-residences-qobxgpsb"}, {"Title": "Green Terrain, Cheras", "Property / Area": "Green Terrain, Cheras", "Room Type": "Room", "Bedrooms": 1, "Bathrooms": 1, "Price / month (RM)": 750.0, "Price / year (RM)": 9000.0, "Size (sqft)": 150, "Furnishing": "Partially Furnished", "Rent Type": "Monthly", "Min Duration (months)": 12, "Link": "https://speedhome.com/details/green-terrain-cheras-wyfkexrb"}, {"Title": "V-Residensi Selayang Heights, Batu Caves", "Property / Area": "V-Residensi Selayang Heights, Batu Caves", "Room Type": "Room", "Bedrooms": 1, "Bathrooms": 1, "Price / month (RM)": 385.0, "Price / year (RM)": 4620.0, "Size (sqft)": 170, "Furnishing": "Fully Furnished", "Rent Type": "Monthly", "Min Duration (months)": 12, "Link": "https://speedhome.com/details/vresidensi-selayang-heights-batu-caves-skorteas"}, {"Title": "M Arisa Sentul, Kuala Lumpur", "Property / Area": "M Arisa Sentul, Kuala Lumpur", "Room Type": "Room", "Bedrooms": 1, "Bathrooms": 1, "Price / month (RM)": 850.0, "Price / year (RM)": 10200.0, "Size (sqft)": null, "Furnishing": "Partially Furnished", "Rent Type": "Monthly", "Min Duration (months)": 12, "Link": "https://speedhome.com/details/m-arisa-sentul-kuala-lumpur-kcmqdghv"}, {"Title": "M Arisa Sentul, Kuala Lumpur", "Property / Area": "M Arisa Sentul, Kuala Lumpur", "Room Type": "Room", "Bedrooms": 1, "Bathrooms": 1, "Price / month (RM)": 950.0, "Price / year (RM)": 11400.0, "Size (sqft)": null, "Furnishing": "Partially Furnished", "Rent Type": "Monthly", "Min Duration (months)": 12, "Link": "https://speedhome.com/details/m-arisa-sentul-kuala-lumpur-cnouackc"}, {"Title": "M Arisa Sentul, Kuala Lumpur", "Property / Area": "M Arisa Sentul, Kuala Lumpur", "Room Type": "Room", "Bedrooms": 1, "Bathrooms": 1, "Price / month (RM)": 1150.0, "Price / year (RM)": 13800.0, "Size (sqft)": 300, "Furnishing": "Partially Furnished", "Rent Type": "Monthly", "Min Duration (months)": 12, "Link": "https://speedhome.com/details/m-arisa-sentul-kuala-lumpur-sfropprt"}, {"Title": "Residensi Alami, Shah Alam", "Property / Area": "Residensi Alami, Shah Alam", "Room Type": "3BR", "Bedrooms": 3, "Bathrooms": 2, "Price / month (RM)": 2500.0, "Price / year (RM)": 30000.0, "Size (sqft)": 1080, "Furnishing": "Fully Furnished", "Rent Type": "Monthly", "Min Duration (months)": 12, "Link": "https://speedhome.com/details/residensi-alami-shah-alam-gvwyqzft"}, {"Title": "Razak City Residences, Kuala Lumpur", "Property / Area": "Razak City Residences, Kuala Lumpur", "Room Type": "3BR", "Bedrooms": 3, "Bathrooms": 3, "Price / month (RM)": 3000.0, "Price / year (RM)": 36000.0, "Size (sqft)": 1045, "Furnishing": "Partially Furnished", "Rent Type": "Monthly", "Min Duration (months)": 12, "Link": "https://speedhome.com/details/razak-city-residences-kuala-lumpur-ufncwwgh"}, {"Title": "Vivo Executive Apartment, Bandar Cassia", "Property / Area": "Vivo Executive Apartment, Bandar Cassia", "Room Type": "3BR", "Bedrooms": 3, "Bathrooms": 2, "Price / month (RM)": 1800.0, "Price / year (RM)": 21600.0, "Size (sqft)": 730, "Furnishing": "Partially Furnished", "Rent Type": "Monthly", "Min Duration (months)": 12, "Link": "https://speedhome.com/details/vivo-executive-apartment-bandar-cassia-wjuhbxyh"}, {"Title": "Bennington Residences, Setapak", "Property / Area": "Bennington Residences, Setapak", "Room Type": "4BR", "Bedrooms": 4, "Bathrooms": 3, "Price / month (RM)": 2300.0, "Price / year (RM)": 27600.0, "Size (sqft)": 1445, "Furnishing": "Partially Furnished", "Rent Type": "Monthly", "Min Duration (months)": 12, "Link": "https://speedhome.com/details/bennington-residences-setapak-icmfiurq"}, {"Title": "Bennington Residences, Setapak", "Property / Area": "Bennington Residences, Setapak", "Room Type": "3BR", "Bedrooms": 3, "Bathrooms": 2, "Price / month (RM)": 1800.0, "Price / year (RM)": 21600.0, "Size (sqft)": 1236, "Furnishing": "Partially Furnished", "Rent Type": "Monthly", "Min Duration (months)": 12, "Link": "https://speedhome.com/details/bennington-residences-setapak-lnmvjnbn"}, {"Title": "Bennington Residences, Setapak", "Property / Area": "Bennington Residences, Setapak", "Room Type": "3BR", "Bedrooms": 3, "Bathrooms": 2, "Price / month (RM)": 1800.0, "Price / year (RM)": 21600.0, "Size (sqft)": 1236, "Furnishing": "Partially Furnished", "Rent Type": "Monthly", "Min Duration (months)": 12, "Link": "https://speedhome.com/details/bennington-residences-setapak-wrycoorn"}, {"Title": "EdgeWood Residences @ SkySanctuary, Kuala Lumpur", "Property / Area": "EdgeWood Residences @ SkySanctuary, Kuala Lumpur", "Room Type": "3BR", "Bedrooms": 3, "Bathrooms": 2, "Price / month (RM)": 2300.0, "Price / year (RM)": 27600.0, "Size (sqft)": 1096, "Furnishing": "Fully Furnished", "Rent Type": "Monthly", "Min Duration (months)": 12, "Link": "https://speedhome.com/details/edgewood-residences-skysanctuary-kuala-lumpur-heinvwao"}, {"Title": "Kondominium Selayang 228, Batu Caves", "Property / Area": "Kondominium Selayang 228, Batu Caves", "Room Type": "3BR", "Bedrooms": 3, "Bathrooms": 2, "Price / month (RM)": 1800.0, "Price / year (RM)": 21600.0, "Size (sqft)": 965, "Furnishing": "Fully Furnished", "Rent Type": "Monthly", "Min Duration (months)": 12, "Link": "https://speedhome.com/details/kondominium-selayang-228-jrfcseci"}, {"Title": "Block A (Semarak) Taman Raintree, Batu Caves", "Property / Area": "Block A (Semarak) Taman Raintree, Batu Caves", "Room Type": "3BR", "Bedrooms": 3, "Bathrooms": 2, "Price / month (RM)": 1500.0, "Price / year (RM)": 18000.0, "Size (sqft)": 1096, "Furnishing": "Unfurnished", "Rent Type": "Monthly", "Min Duration (months)": 12, "Link": "https://speedhome.com/details/block-a-semarak-taman-raintree-batu-caves-lrevfcrw"}, {"Title": "Epic Residences, Johor Bahru", "Property / Area": "Epic Residences, Johor Bahru", "Room Type": "3BR", "Bedrooms": 3, "Bathrooms": 2, "Price / month (RM)": 2500.0, "Price / year (RM)": 30000.0, "Size (sqft)": 1206, "Furnishing": "Partially Furnished", "Rent Type": "Monthly", "Min Duration (months)": 12, "Link": "https://speedhome.com/details/epic-residences-swbmhwtb"}, {"Title": "Razak City Residences, Kuala Lumpur", "Property / Area": "Razak City Residences, Kuala Lumpur", "Room Type": "2BR", "Bedrooms": 2, "Bathrooms": 2, "Price / month (RM)": 2400.0, "Price / year (RM)": 28800.0, "Size (sqft)": 1640, "Furnishing": "Partially Furnished", "Rent Type": "Monthly", "Min Duration (months)": 12, "Link": "https://speedhome.com/details/razak-city-residences-kuala-lumpur-jkvoggrd"}, {"Title": "M Vertica, Kuala Lumpur", "Property / Area": "M Vertica, Kuala Lumpur", "Room Type": "Room", "Bedrooms": 1, "Bathrooms": 1, "Price / month (RM)": 1150.0, "Price / year (RM)": 13800.0, "Size (sqft)": null, "Furnishing": "Fully Furnished", "Rent Type": "Monthly", "Min Duration (months)": 12, "Link": "https://speedhome.com/details/m-vertica-kuala-lumpur-htmxkixz"}, {"Title": "The Clio 2 Residences, Putrajaya", "Property / Area": "The Clio 2 Residences, Putrajaya", "Room Type": "3BR", "Bedrooms": 3, "Bathrooms": 2, "Price / month (RM)": 3500.0, "Price / year (RM)": 42000.0, "Size (sqft)": 970, "Furnishing": "Fully Furnished", "Rent Type": "Monthly", "Min Duration (months)": 12, "Link": "https://speedhome.com/details/the-clio-2-residences-putrajaya-qbxtxgqs"}, {"Title": "KSL Residences, Johor Bahru", "Property / Area": "KSL Residences, Johor Bahru", "Room Type": "3BR", "Bedrooms": 3, "Bathrooms": 3, "Price / month (RM)": 2600.0, "Price / year (RM)": 31200.0, "Size (sqft)": 1090, "Furnishing": "Partially Furnished", "Rent Type": "Monthly", "Min Duration (months)": 12, "Link": "https://speedhome.com/details/ksl-residences-johor-bahru-rbjwbzpr"}, {"Title": "B11 Parkland Residence, Cheras", "Property / Area": "B11 Parkland Residence, Cheras", "Room Type": "3BR", "Bedrooms": 3, "Bathrooms": 2, "Price / month (RM)": 2300.0, "Price / year (RM)": 27600.0, "Size (sqft)": 875, "Furnishing": "Fully Furnished", "Rent Type": "Monthly", "Min Duration (months)": 12, "Link": "https://speedhome.com/details/b11-parkland-residence-cheras-synhuzsi"}, {"Title": "Res 280 Condominium, Selayang", "Property / Area": "Res 280 Condominium, Selayang", "Room Type": "Room", "Bedrooms": 1, "Bathrooms": 1, "Price / month (RM)": 700.0, "Price / year (RM)": 8400.0, "Size (sqft)": 150, "Furnishing": "Fully Furnished", "Rent Type": "Monthly", "Min Duration (months)": 12, "Link": "https://speedhome.com/details/res-280-condominium-selayang-gggujyos"}, {"Title": "Res 280 Condominium, Selayang", "Property / Area": "Res 280 Condominium, Selayang", "Room Type": "Room", "Bedrooms": 1, "Bathrooms": 1, "Price / month (RM)": 900.0, "Price / year (RM)": 10800.0, "Size (sqft)": null, "Furnishing": "Fully Furnished", "Rent Type": "Monthly", "Min Duration (months)": 6, "Link": "https://speedhome.com/details/res-280-condominium-selayang-xzzfjzta"}, {"Title": "M Centura, Sentul", "Property / Area": "M Centura, Sentul", "Room Type": "2BR", "Bedrooms": 2, "Bathrooms": 1, "Price / month (RM)": 2200.0, "Price / year (RM)": 26400.0, "Size (sqft)": 650, "Furnishing": "Partially Furnished", "Rent Type": "Monthly", "Min Duration (months)": 12, "Link": "https://speedhome.com/details/m-centura-sentul-llhulgla"}, {"Title": "Vipod Residences, Kuala Lumpur", "Property / Area": "Vipod Residences, Kuala Lumpur", "Room Type": "Room", "Bedrooms": 1, "Bathrooms": 1, "Price / month (RM)": 2300.0, "Price / year (RM)": 27600.0, "Size (sqft)": 125, "Furnishing": "Fully Furnished", "Rent Type": "Monthly", "Min Duration (months)": 12, "Link": "https://speedhome.com/details/vipod-residences-kuala-lumpur-tpouexza"}, {"Title": "Ashton Eco Horizon, Batu Kawan", "Property / Area": "Ashton Eco Horizon, Batu Kawan", "Room Type": "4BR", "Bedrooms": 4, "Bathrooms": 4, "Price / month (RM)": 2888.0, "Price / year (RM)": 34656.0, "Size (sqft)": 2290, "Furnishing": "Partially Furnished", "Rent Type": "Monthly", "Min Duration (months)": 12, "Link": "https://speedhome.com/details/ashton-eco-horizon-batu-kawan-qyhrccms"}, {"Title": "Bandar Bukit Tinggi 2, Klang", "Property / Area": "Bandar Bukit Tinggi 2, Klang", "Room Type": "3BR", "Bedrooms": 3, "Bathrooms": 2, "Price / month (RM)": 950.0, "Price / year (RM)": 11400.0, "Size (sqft)": 650, "Furnishing": "Partially Furnished", "Rent Type": "Monthly", "Min Duration (months)": 6, "Link": "https://speedhome.com/details/bandar-bukit-tinggi-2-klang-bwepcegf"}, {"Title": "Taman PD Jasmin, Port Dickson", "Property / Area": "Taman PD Jasmin, Port Dickson", "Room Type": "6BR", "Bedrooms": 6, "Bathrooms": 4, "Price / month (RM)": 4500.0, "Price / year (RM)": 54000.0, "Size (sqft)": 2800, "Furnishing": "Partially Furnished", "Rent Type": "Monthly", "Min Duration (months)": 12, "Link": "https://speedhome.com/details/no20-home-qpapbiqt"}, {"Title": "Jalan Pantai, Port Dickson", "Property / Area": "Jalan Pantai, Port Dickson", "Room Type": "Room", "Bedrooms": 1, "Bathrooms": 1, "Price / month (RM)": 900.0, "Price / year (RM)": 10800.0, "Size (sqft)": null, "Furnishing": "Unfurnished", "Rent Type": "Monthly", "Min Duration (months)": 6, "Link": "https://speedhome.com/details/234roombed-ypapjcku"}, {"Title": "The Parque Residences, Telok Panglima Garang", "Property / Area": "The Parque Residences, Telok Panglima Garang", "Room Type": "2BR", "Bedrooms": 2, "Bathrooms": 2, "Price / month (RM)": 1500.0, "Price / year (RM)": 18000.0, "Size (sqft)": 925, "Furnishing": "Fully Furnished", "Rent Type": "Monthly", "Min Duration (months)": 12, "Link": "https://speedhome.com/details/the-parque-residences-telok-panglima-garang-cqtcqrfg"}, {"Title": "The Parque Residences, Telok Panglima Garang", "Property / Area": "The Parque Residences, Telok Panglima Garang", "Room Type": "2BR", "Bedrooms": 2, "Bathrooms": 2, "Price / month (RM)": 1500.0, "Price / year (RM)": 18000.0, "Size (sqft)": 979, "Furnishing": "Fully Furnished", "Rent Type": "Monthly", "Min Duration (months)": 12, "Link": "https://speedhome.com/details/the-parque-residences-telok-panglima-garang-owujiqta"}, {"Title": "The Parque Residences, Telok Panglima Garang", "Property / Area": "The Parque Residences, Telok Panglima Garang", "Room Type": "1BR", "Bedrooms": 1, "Bathrooms": 1, "Price / month (RM)": 1300.0, "Price / year (RM)": 15600.0, "Size (sqft)": 721, "Furnishing": "Fully Furnished", "Rent Type": "Monthly", "Min Duration (months)": 12, "Link": "https://speedhome.com/details/the-parque-residences-telok-panglima-garang-jelsdjey"}, {"Title": "Berkeley Uptown Residences, Klang", "Property / Area": "Berkeley Uptown Residences, Klang", "Room Type": "2BR", "Bedrooms": 2, "Bathrooms": 2, "Price / month (RM)": 1700.0, "Price / year (RM)": 20400.0, "Size (sqft)": 859, "Furnishing": "Partially Furnished", "Rent Type": "Monthly", "Min Duration (months)": 12, "Link": "https://speedhome.com/details/berkeley-uptown-residences-ikgtftlj"}, {"Title": "Jalan Pantai, Port Dickson", "Property / Area": "Jalan Pantai, Port Dickson", "Room Type": "Room", "Bedrooms": 1, "Bathrooms": 1, "Price / month (RM)": 300.0, "Price / year (RM)": 3600.0, "Size (sqft)": null, "Furnishing": "Unfurnished", "Rent Type": "Monthly", "Min Duration (months)": 12, "Link": "https://speedhome.com/details/shop-lot-ygcbxscv"}, {"Title": "The Parque Residences, Telok Panglima Garang", "Property / Area": "The Parque Residences, Telok Panglima Garang", "Room Type": "2BR", "Bedrooms": 2, "Bathrooms": 2, "Price / month (RM)": 1500.0, "Price / year (RM)": 18000.0, "Size (sqft)": 925, "Furnishing": "Partially Furnished", "Rent Type": "Monthly", "Min Duration (months)": 12, "Link": "https://speedhome.com/details/the-parque-residences-telok-panglima-garang-chmjtabr"}, {"Title": "99 Residence, Batu Caves", "Property / Area": "99 Residence, Batu Caves", "Room Type": "3BR", "Bedrooms": 3, "Bathrooms": 3, "Price / month (RM)": 3200.0, "Price / year (RM)": 38400.0, "Size (sqft)": 1220, "Furnishing": "Fully Furnished", "Rent Type": "Monthly", "Min Duration (months)": 12, "Link": "https://speedhome.com/details/99-residence-batu-caves-intaxpqd"}, {"Title": "Kajang 2, Kajang", "Property / Area": "Kajang 2, Kajang", "Room Type": "1BR", "Bedrooms": 1, "Bathrooms": 1, "Price / month (RM)": 1100.0, "Price / year (RM)": 13200.0, "Size (sqft)": 550, "Furnishing": "Unfurnished", "Rent Type": "Monthly", "Min Duration (months)": 6, "Link": "https://speedhome.com/details/kajang-2-kajang-kzjwbqzn"}, {"Title": "The Valley Residences Skysierra, Setiawangsa", "Property / Area": "The Valley Residences Skysierra, Setiawangsa", "Room Type": "1BR", "Bedrooms": 1, "Bathrooms": 1, "Price / month (RM)": 1800.0, "Price / year (RM)": 21600.0, "Size (sqft)": 300, "Furnishing": "Fully Furnished", "Rent Type": "Monthly", "Min Duration (months)": 12, "Link": "https://speedhome.com/details/the-valley-residences-skysierra-setiawangsa-jactvhdc"}, {"Title": "Admiral Residences, Melaka", "Property / Area": "Admiral Residences, Melaka", "Room Type": "3BR", "Bedrooms": 3, "Bathrooms": 2, "Price / month (RM)": 2000.0, "Price / year (RM)": 24000.0, "Size (sqft)": 1096, "Furnishing": "Fully Furnished", "Rent Type": "Monthly", "Min Duration (months)": 12, "Link": "https://speedhome.com/details/admiral-residences-melaka-wjupitac"}, {"Title": "Setia City Residences, Shah Alam", "Property / Area": "Setia City Residences, Shah Alam", "Room Type": "3BR", "Bedrooms": 3, "Bathrooms": 2, "Price / month (RM)": 2500.0, "Price / year (RM)": 30000.0, "Size (sqft)": 985, "Furnishing": "Partially Furnished", "Rent Type": "Monthly", "Min Duration (months)": 12, "Link": "https://speedhome.com/details/setia-city-residences-shah-alam-icshfvlf"}, {"Title": "Havana Residences, Bayan Lepas", "Property / Area": "Havana Residences, Bayan Lepas", "Room Type": "3BR", "Bedrooms": 3, "Bathrooms": 2, "Price / month (RM)": 1600.0, "Price / year (RM)": 19200.0, "Size (sqft)": 900, "Furnishing": "Partially Furnished", "Rent Type": "Monthly", "Min Duration (months)": 12, "Link": "https://speedhome.com/details/havana-residences-bayan-lepas-drifuxmt"}, {"Title": "MH Platinum 2 Residences, Setapak", "Property / Area": "MH Platinum 2 Residences, Setapak", "Room Type": "3BR", "Bedrooms": 3, "Bathrooms": 2, "Price / month (RM)": 1900.0, "Price / year (RM)": 22800.0, "Size (sqft)": 650, "Furnishing": "Unfurnished", "Rent Type": "Monthly", "Min Duration (months)": 12, "Link": "https://speedhome.com/details/mh-platinum-2-residences-setapak-svmtlhgz"}, {"Title": "Trellis Residences, Johor Bahru", "Property / Area": "Trellis Residences, Johor Bahru", "Room Type": "2BR", "Bedrooms": 2, "Bathrooms": 1, "Price / month (RM)": 2500.0, "Price / year (RM)": 30000.0, "Size (sqft)": 650, "Furnishing": "Partially Furnished", "Rent Type": "Monthly", "Min Duration (months)": 12, "Link": "https://speedhome.com/details/the-threllis-tkkmjnip"}, {"Title": "Duta Park Residences, Kuala Lumpur", "Property / Area": "Duta Park Residences, Kuala Lumpur", "Room Type": "3BR", "Bedrooms": 3, "Bathrooms": 2, "Price / month (RM)": 4000.0, "Price / year (RM)": 48000.0, "Size (sqft)": 1129, "Furnishing": "Fully Furnished", "Rent Type": "Monthly", "Min Duration (months)": 12, "Link": "https://speedhome.com/details/duta-park-residences-pqdvkwmw"}, {"Title": "Magna Ville, Batu Caves", "Property / Area": "Magna Ville, Batu Caves", "Room Type": "Room", "Bedrooms": 1, "Bathrooms": 1, "Price / month (RM)": 500.0, "Price / year (RM)": 6000.0, "Size (sqft)": 200, "Furnishing": "Partially Furnished", "Rent Type": "Monthly", "Min Duration (months)": 12, "Link": "https://speedhome.com/details/magna-ville-batu-caves-uygcojrb"}, {"Title": "Savana Residences, Simpang Ampat", "Property / Area": "Savana Residences, Simpang Ampat", "Room Type": "4BR", "Bedrooms": 4, "Bathrooms": 2, "Price / month (RM)": 2500.0, "Price / year (RM)": 30000.0, "Size (sqft)": 1184, "Furnishing": "Fully Furnished", "Rent Type": "Monthly", "Min Duration (months)": 12, "Link": "https://speedhome.com/details/savana-residence-mnvozbbv"}, {"Title": "Razak City Residences, Kuala Lumpur", "Property / Area": "Razak City Residences, Kuala Lumpur", "Room Type": "Room", "Bedrooms": 1, "Bathrooms": 1, "Price / month (RM)": 1400.0, "Price / year (RM)": 16800.0, "Size (sqft)": 1140, "Furnishing": "Fully Furnished", "Rent Type": "Monthly", "Min Duration (months)": 12, "Link": "https://speedhome.com/details/razak-city-residences-kuala-lumpur-aqdjnkve"}, {"Title": "Havana Residences, Bayan Lepas", "Property / Area": "Havana Residences, Bayan Lepas", "Room Type": "3BR", "Bedrooms": 3, "Bathrooms": 2, "Price / month (RM)": 3500.0, "Price / year (RM)": 42000.0, "Size (sqft)": 950, "Furnishing": "Fully Furnished", "Rent Type": "Monthly", "Min Duration (months)": 12, "Link": "https://speedhome.com/details/havana-residences-bayan-lepas-swbkbzow"}, {"Title": "AraTre' Residences, Petaling Jaya", "Property / Area": "AraTre' Residences, Petaling Jaya", "Room Type": "Room", "Bedrooms": 1, "Bathrooms": 1, "Price / month (RM)": 820.0, "Price / year (RM)": 9840.0, "Size (sqft)": 650, "Furnishing": "Fully Furnished", "Rent Type": "Monthly", "Min Duration (months)": 6, "Link": "https://speedhome.com/details/aratre-residences-petaling-jaya-lfaolhif"}, {"Title": "Menara Menjalara, Bandar Menjalara", "Property / Area": "Menara Menjalara, Bandar Menjalara", "Room Type": "Room", "Bedrooms": 1, "Bathrooms": 1, "Price / month (RM)": 750.0, "Price / year (RM)": 9000.0, "Size (sqft)": 150, "Furnishing": "Partially Furnished", "Rent Type": "Monthly", "Min Duration (months)": 6, "Link": "https://speedhome.com/details/menara-menjalara-bandar-menjalara-pgytepsb"}, {"Title": "Jaya One Residences, Petaling Jaya", "Property / Area": "Jaya One Residences, Petaling Jaya", "Room Type": "1BR", "Bedrooms": 1, "Bathrooms": 1, "Price / month (RM)": 2400.0, "Price / year (RM)": 28800.0, "Size (sqft)": 780, "Furnishing": "Fully Furnished", "Rent Type": "Monthly", "Min Duration (months)": 6, "Link": "https://speedhome.com/details/jaya-one-residences-petaling-jaya-nxkoiuzn"}, {"Title": "Zentro Residences, Puchong", "Property / Area": "Zentro Residences, Puchong", "Room Type": "3BR", "Bedrooms": 3, "Bathrooms": 2, "Price / month (RM)": 2600.0, "Price / year (RM)": 31200.0, "Size (sqft)": 959, "Furnishing": "Fully Furnished", "Rent Type": "Monthly", "Min Duration (months)": 12, "Link": "https://speedhome.com/details/zentro-residences-puchong-enrgejaz"}, {"Title": "One Cochrane Residences, Kuala Lumpur", "Property / Area": "One Cochrane Residences, Kuala Lumpur", "Room Type": "2BR", "Bedrooms": 2, "Bathrooms": 2, "Price / month (RM)": 3600.0, "Price / year (RM)": 43200.0, "Size (sqft)": 980, "Furnishing": "Fully Furnished", "Rent Type": "Monthly", "Min Duration (months)": 12, "Link": "https://speedhome.com/details/one-cochrane-residences-kuala-lumpur-qzarzniz"}, {"Title": "Sinaran Residences, Batu Kawan", "Property / Area": "Sinaran Residences, Batu Kawan", "Room Type": "Room", "Bedrooms": 1, "Bathrooms": 1, "Price / month (RM)": 850.0, "Price / year (RM)": 10200.0, "Size (sqft)": null, "Furnishing": "Fully Furnished", "Rent Type": "Monthly", "Min Duration (months)": 12, "Link": "https://speedhome.com/details/sinaran-residences-batu-kawan-wvxznhwk"}, {"Title": "Bennington Residences, Setapak", "Property / Area": "Bennington Residences, Setapak", "Room Type": "3BR", "Bedrooms": 3, "Bathrooms": 2, "Price / month (RM)": 2200.0, "Price / year (RM)": 26400.0, "Size (sqft)": 1572, "Furnishing": "Partially Furnished", "Rent Type": "Monthly", "Min Duration (months)": 12, "Link": "https://speedhome.com/details/bennington-residences-setapak-iutxpikj"}, {"Title": "Bennington Residences, Setapak", "Property / Area": "Bennington Residences, Setapak", "Room Type": "4BR", "Bedrooms": 4, "Bathrooms": 2, "Price / month (RM)": 2200.0, "Price / year (RM)": 26400.0, "Size (sqft)": 1239, "Furnishing": "Partially Furnished", "Rent Type": "Monthly", "Min Duration (months)": 12, "Link": "https://speedhome.com/details/bennington-residences-setapak-bwzslxcn"}, {"Title": "Bennington Residences, Setapak", "Property / Area": "Bennington Residences, Setapak", "Room Type": "3BR", "Bedrooms": 3, "Bathrooms": 2, "Price / month (RM)": 2300.0, "Price / year (RM)": 27600.0, "Size (sqft)": 1572, "Furnishing": "Partially Furnished", "Rent Type": "Monthly", "Min Duration (months)": 12, "Link": "https://speedhome.com/details/bennington-residences-setapak-lvrkpnjt"}, {"Title": "(SPEEDHOME TESTING, DONT REQUEST CHAT) Cheras Perdana, Cheras", "Property / Area": "(SPEEDHOME TESTING, DONT REQUEST CHAT) Cheras Perdana, Cheras", "Room Type": "3BR", "Bedrooms": 3, "Bathrooms": 2, "Price / month (RM)": 2251.0, "Price / year (RM)": 27012.0, "Size (sqft)": 251, "Furnishing": "Unfurnished", "Rent Type": "Monthly", "Min Duration (months)": 12, "Link": "https://speedhome.com/details/speedhome-testing-dont-request-chat-cheras-perdana-cheras-wzkciuur"}, {"Title": "The Haven Lakeside Residences, Ipoh", "Property / Area": "The Haven Lakeside Residences, Ipoh", "Room Type": "3BR", "Bedrooms": 3, "Bathrooms": 2, "Price / month (RM)": 2000.0, "Price / year (RM)": 24000.0, "Size (sqft)": 930, "Furnishing": "Fully Furnished", "Rent Type": "Monthly", "Min Duration (months)": 12, "Link": "https://speedhome.com/details/the-haven-lakeside-residences-xyudvwsa"}, {"Title": "Gaia Residences, Rawang", "Property / Area": "Gaia Residences, Rawang", "Room Type": "3BR", "Bedrooms": 3, "Bathrooms": 2, "Price / month (RM)": 2500.0, "Price / year (RM)": 30000.0, "Size (sqft)": 900, "Furnishing": "Fully Furnished", "Rent Type": "Monthly", "Min Duration (months)": 12, "Link": "https://speedhome.com/details/gaia-residences-rawang-nuycicqg"}, {"Title": "Bennington Residences, Kuala Lumpur", "Property / Area": "Bennington Residences, Kuala Lumpur", "Room Type": "4BR", "Bedrooms": 4, "Bathrooms": 3, "Price / month (RM)": 2000.0, "Price / year (RM)": 24000.0, "Size (sqft)": 1453, "Furnishing": "Unfurnished", "Rent Type": "Monthly", "Min Duration (months)": 12, "Link": "https://speedhome.com/details/bennington-residences-kuala-lumpur-pljtrbcd"}, {"Title": "Nidoz Residences, Desa Petaling", "Property / Area": "Nidoz Residences, Desa Petaling", "Room Type": "Room", "Bedrooms": 1, "Bathrooms": 1, "Price / month (RM)": 750.0, "Price / year (RM)": 9000.0, "Size (sqft)": null, "Furnishing": "Unfurnished", "Rent Type": "Monthly", "Min Duration (months)": 12, "Link": "https://speedhome.com/details/nidoz-residences-desa-petaling-alrhdqjx"}, {"Title": "H2O Residences, Petaling Jaya", "Property / Area": "H2O Residences, Petaling Jaya", "Room Type": "2BR", "Bedrooms": 2, "Bathrooms": 2, "Price / month (RM)": 2200.0, "Price / year (RM)": 26400.0, "Size (sqft)": 754, "Furnishing": "Partially Furnished", "Rent Type": "Monthly", "Min Duration (months)": 12, "Link": "https://speedhome.com/details/h2o-residences-petaling-jaya-sswfujaz"}, {"Title": "Saville, Cheras", "Property / Area": "Saville, Cheras", "Room Type": "3BR", "Bedrooms": 3, "Bathrooms": 2, "Price / month (RM)": 2700.0, "Price / year (RM)": 32400.0, "Size (sqft)": 1280, "Furnishing": "Fully Furnished", "Rent Type": "Monthly", "Min Duration (months)": 12, "Link": "https://speedhome.com/details/saville-cheras-miqujqhd"}, {"Title": "The Pano, Kuala Lumpur", "Property / Area": "The Pano, Kuala Lumpur", "Room Type": "1BR", "Bedrooms": 1, "Bathrooms": 1, "Price / month (RM)": 1700.0, "Price / year (RM)": 20400.0, "Size (sqft)": 500, "Furnishing": "Partially Furnished", "Rent Type": "Monthly", "Min Duration (months)": 12, "Link": "https://speedhome.com/details/the-pano-kuala-lumpur-bzxrvqbz"}, {"Title": "Jalan Meru, Klang", "Property / Area": "Jalan Meru, Klang", "Room Type": "4BR", "Bedrooms": 4, "Bathrooms": 3, "Price / month (RM)": 2100.0, "Price / year (RM)": 25200.0, "Size (sqft)": 1665, "Furnishing": "Unfurnished", "Rent Type": "Monthly", "Min Duration (months)": 12, "Link": "https://speedhome.com/details/jalan-meru-klang-xaqytkqp"}, {"Title": "Sqwhere Service Residence, Sungai Buloh", "Property / Area": "Sqwhere Service Residence, Sungai Buloh", "Room Type": "4BR", "Bedrooms": 4, "Bathrooms": 4, "Price / month (RM)": 5500.0, "Price / year (RM)": 66000.0, "Size (sqft)": 2200, "Furnishing": "Partially Furnished", "Rent Type": "Monthly", "Min Duration (months)": 12, "Link": "https://speedhome.com/details/sqwhere-service-residence-sungai-buloh-bniieqhp"}, {"Title": "One Cochrane Residences, Kuala Lumpur", "Property / Area": "One Cochrane Residences, Kuala Lumpur", "Room Type": "Room", "Bedrooms": 1, "Bathrooms": 1, "Price / month (RM)": 1690.0, "Price / year (RM)": 20280.0, "Size (sqft)": null, "Furnishing": "Fully Furnished", "Rent Type": "Monthly", "Min Duration (months)": 12, "Link": "https://speedhome.com/details/one-cochrane-residence--xjojsnyc"}, {"Title": "Peony Square Residences, Cameron Highlands", "Property / Area": "Peony Square Residences, Cameron Highlands", "Room Type": "3BR", "Bedrooms": 3, "Bathrooms": 2, "Price / month (RM)": 1800.0, "Price / year (RM)": 21600.0, "Size (sqft)": 1180, "Furnishing": "Partially Furnished", "Rent Type": "Monthly", "Min Duration (months)": 12, "Link": "https://speedhome.com/details/peony-square-residences-cameron-highlands-ttlfsxie"}, {"Title": "MET 1 Residences, Kuala Lumpur", "Property / Area": "MET 1 Residences, Kuala Lumpur", "Room Type": "1BR", "Bedrooms": 1, "Bathrooms": 1, "Price / month (RM)": 3259.0, "Price / year (RM)": 39108.0, "Size (sqft)": 677, "Furnishing": "Fully Furnished", "Rent Type": "Monthly", "Min Duration (months)": 6, "Link": "https://speedhome.com/details/met-1-residences-kuala-lumpur-uiachrkj"}, {"Title": "Palmyra Residences, Bangi", "Property / Area": "Palmyra Residences, Bangi", "Room Type": "3BR", "Bedrooms": 3, "Bathrooms": 2, "Price / month (RM)": 1950.0, "Price / year (RM)": 23400.0, "Size (sqft)": 1070, "Furnishing": "Partially Furnished", "Rent Type": "Monthly", "Min Duration (months)": 12, "Link": "https://speedhome.com/details/palmyra-residences-bangi-wqoosgti"}, {"Title": "Landmark Residence, Bandar Sungai Long (Fully Furnished Budget Room Nearby To MRT)", "Property / Area": "Landmark Residence, Bandar Sungai Long (Fully Furnished Budget Room Nearby To MRT)", "Room Type": "Room", "Bedrooms": 1, "Bathrooms": 1, "Price / month (RM)": 600.0, "Price / year (RM)": 7200.0, "Size (sqft)": null, "Furnishing": "Fully Furnished", "Rent Type": "Monthly", "Min Duration (months)": 12, "Link": "https://speedhome.com/details/landmark-residence-bandar-mahkota-cheras-fully-furnished-single-room-nearby-to-mrt-wftlbuub"}, {"Title": "Landmark Residence, Bandar Mahkota Cheras (Fully Furnished Budget Room Nearby To MRT)", "Property / Area": "Landmark Residence, Bandar Mahkota Cheras (Fully Furnished Budget Room Nearby To MRT)", "Room Type": "Room", "Bedrooms": 1, "Bathrooms": 1, "Price / month (RM)": 600.0, "Price / year (RM)": 7200.0, "Size (sqft)": null, "Furnishing": "Fully Furnished", "Rent Type": "Monthly", "Min Duration (months)": 12, "Link": "https://speedhome.com/details/landmark-residence-bandar-sungai-long-fully-furnished-single-room-nearby-to-mrt-plrrgsai"}, {"Title": "M Arisa Sentul, Kuala Lumpur", "Property / Area": "M Arisa Sentul, Kuala Lumpur", "Room Type": "2BR", "Bedrooms": 2, "Bathrooms": 2, "Price / month (RM)": 2400.0, "Price / year (RM)": 28800.0, "Size (sqft)": 708, "Furnishing": "Fully Furnished", "Rent Type": "Monthly", "Min Duration (months)": 12, "Link": "https://speedhome.com/details/m-arisa-sentul-kuala-lumpur-inklgkgb"}, {"Title": "M Arisa Sentul, Kuala Lumpur", "Property / Area": "M Arisa Sentul, Kuala Lumpur", "Room Type": "2BR", "Bedrooms": 2, "Bathrooms": 2, "Price / month (RM)": 2400.0, "Price / year (RM)": 28800.0, "Size (sqft)": 708, "Furnishing": "Fully Furnished", "Rent Type": "Monthly", "Min Duration (months)": 12, "Link": "https://speedhome.com/details/m-arisa-fpqlklfp"}, {"Title": "The Ridge KL East", "Property / Area": "The Ridge KL East", "Room Type": "Studio", "Bedrooms": 0, "Bathrooms": 1, "Price / month (RM)": 2100.0, "Price / year (RM)": 25200.0, "Size (sqft)": 651, "Furnishing": "Fully Furnished", "Rent Type": "Monthly", "Min Duration (months)": 6, "Link": "https://speedhome.com/details/the-ridge-kl-east-udaahhco"}, {"Title": "Corner Lot Taman Kirby, Labu", "Property / Area": "Corner Lot Taman Kirby, Labu", "Room Type": "3BR", "Bedrooms": 3, "Bathrooms": 2, "Price / month (RM)": 1500.0, "Price / year (RM)": 18000.0, "Size (sqft)": 1400, "Furnishing": "Partially Furnished", "Rent Type": "Monthly", "Min Duration (months)": 6, "Link": "https://speedhome.com/details/kirby-zfsuqdrj"}, {"Title": "Arena Residences, Sepang", "Property / Area": "Arena Residences, Sepang", "Room Type": "3BR", "Bedrooms": 3, "Bathrooms": 2, "Price / month (RM)": 2000.0, "Price / year (RM)": 24000.0, "Size (sqft)": 904, "Furnishing": "Fully Furnished", "Rent Type": "Monthly", "Min Duration (months)": 12, "Link": "https://speedhome.com/details/arena-residences-sepang-qrdcolts"}, {"Title": "Mutiara Hills, Semenyih", "Property / Area": "Mutiara Hills, Semenyih", "Room Type": "4BR", "Bedrooms": 4, "Bathrooms": 3, "Price / month (RM)": 1500.0, "Price / year (RM)": 18000.0, "Size (sqft)": 1500, "Furnishing": "Unfurnished", "Rent Type": "Monthly", "Min Duration (months)": 12, "Link": "https://speedhome.com/details/mutiara-hills-semenyih-kxnwlzab"}, {"Title": "Vivo Executive Apartment, Bandar Cassia", "Property / Area": "Vivo Executive Apartment, Bandar Cassia", "Room Type": "Room", "Bedrooms": 1, "Bathrooms": 1, "Price / month (RM)": 500.0, "Price / year (RM)": 6000.0, "Size (sqft)": 117, "Furnishing": "Partially Furnished", "Rent Type": "Monthly", "Min Duration (months)": 12, "Link": "https://speedhome.com/details/vivo-executive-apartment-bandar-cassia-ogexplyh"}, {"Title": "Admiral Residences, Melaka", "Property / Area": "Admiral Residences, Melaka", "Room Type": "3BR", "Bedrooms": 3, "Bathrooms": 2, "Price / month (RM)": 1650.0, "Price / year (RM)": 19800.0, "Size (sqft)": 1069, "Furnishing": "Partially Furnished", "Rent Type": "Monthly", "Min Duration (months)": 12, "Link": "https://speedhome.com/details/admiral-residences-melaka-swdjmbsy"}, {"Title": "Avenue Crest, Shah Alam", "Property / Area": "Avenue Crest, Shah Alam", "Room Type": "1BR", "Bedrooms": 1, "Bathrooms": 1, "Price / month (RM)": 1150.0, "Price / year (RM)": 13800.0, "Size (sqft)": 560, "Furnishing": "Unfurnished", "Rent Type": "Monthly", "Min Duration (months)": 12, "Link": "https://speedhome.com/details/avenue-crest-shah-alam-gmocsoem"}, {"Title": "Ferringhi Residence 2", "Property / Area": "Ferringhi Residence 2", "Room Type": "3BR", "Bedrooms": 3, "Bathrooms": 3, "Price / month (RM)": 3000.0, "Price / year (RM)": 36000.0, "Size (sqft)": 1500, "Furnishing": "Fully Furnished", "Rent Type": "Monthly", "Min Duration (months)": 12, "Link": "https://speedhome.com/details/ferringhi-residence-2-kxkdpelc"}, {"Title": "Mirai Residences, Kajang", "Property / Area": "Mirai Residences, Kajang", "Room Type": "3BR", "Bedrooms": 3, "Bathrooms": 2, "Price / month (RM)": 2100.0, "Price / year (RM)": 25200.0, "Size (sqft)": 931, "Furnishing": "Fully Furnished", "Rent Type": "Monthly", "Min Duration (months)": 12, "Link": "https://speedhome.com/details/mirai-residences-kajang-ebbtsrsj"}, {"Title": "Pandora Serviced Residences, Subang Jaya", "Property / Area": "Pandora Serviced Residences, Subang Jaya", "Room Type": "1BR", "Bedrooms": 1, "Bathrooms": 1, "Price / month (RM)": 2200.0, "Price / year (RM)": 26400.0, "Size (sqft)": 600, "Furnishing": "Fully Furnished", "Rent Type": "Monthly", "Min Duration (months)": 12, "Link": "https://speedhome.com/details/pandora-serviced-residences-subang-jaya-xokkqhxf"}, {"Title": "Bandar Cassia, Batu Kawan", "Property / Area": "Bandar Cassia, Batu Kawan", "Room Type": "Room", "Bedrooms": 1, "Bathrooms": 1, "Price / month (RM)": 700.0, "Price / year (RM)": 8400.0, "Size (sqft)": 117, "Furnishing": "Partially Furnished", "Rent Type": "Monthly", "Min Duration (months)": 12, "Link": "https://speedhome.com/details/bandar-cassia-batu-kawan-xgcbgwri"}, {"Title": "Seasons Gardens Residences, Wangsamaju", "Property / Area": "Seasons Gardens Residences, Wangsamaju", "Room Type": "3BR", "Bedrooms": 3, "Bathrooms": 2, "Price / month (RM)": 1650.0, "Price / year (RM)": 19800.0, "Size (sqft)": 770, "Furnishing": "Unfurnished", "Rent Type": "Monthly", "Min Duration (months)": 12, "Link": "https://speedhome.com/details/seasons-gardens-residences-wangsamaju-uizaubyw"}, {"Title": "Sentul Point Suite Apartment", "Property / Area": "Sentul Point Suite Apartment", "Room Type": "2BR", "Bedrooms": 2, "Bathrooms": 1, "Price / month (RM)": 1800.0, "Price / year (RM)": 21600.0, "Size (sqft)": 721, "Furnishing": "Fully Furnished", "Rent Type": "Monthly", "Min Duration (months)": 12, "Link": "https://speedhome.com/details/sentul-point-suite-apartment-vdghugze"}, {"Title": "The Valley Residences Skysierra, Setiawangsa", "Property / Area": "The Valley Residences Skysierra, Setiawangsa", "Room Type": "2BR", "Bedrooms": 2, "Bathrooms": 1, "Price / month (RM)": 2000.0, "Price / year (RM)": 24000.0, "Size (sqft)": 800, "Furnishing": "Partially Furnished", "Rent Type": "Monthly", "Min Duration (months)": 12, "Link": "https://speedhome.com/details/the-valley-residences-skysierra-setiawangsa-mcdfdaab"}, {"Title": "Suria Garden, Puchong", "Property / Area": "Suria Garden, Puchong", "Room Type": "3BR", "Bedrooms": 3, "Bathrooms": 2, "Price / month (RM)": 2300.0, "Price / year (RM)": 27600.0, "Size (sqft)": 876, "Furnishing": "Fully Furnished", "Rent Type": "Monthly", "Min Duration (months)": 12, "Link": "https://speedhome.com/details/suria-garden-puchong-irtharoz"}, {"Title": "Avenue Crest, Shah Alam", "Property / Area": "Avenue Crest, Shah Alam", "Room Type": "1BR", "Bedrooms": 1, "Bathrooms": 1, "Price / month (RM)": 1000.0, "Price / year (RM)": 12000.0, "Size (sqft)": 614, "Furnishing": "Partially Furnished", "Rent Type": "Monthly", "Min Duration (months)": 6, "Link": "https://speedhome.com/details/avenue-crest-shah-alam-kjrpssgw"}, {"Title": "Sky Awani 3, Kuala Lumpur", "Property / Area": "Sky Awani 3, Kuala Lumpur", "Room Type": "3BR", "Bedrooms": 3, "Bathrooms": 2, "Price / month (RM)": 2100.0, "Price / year (RM)": 25200.0, "Size (sqft)": 800, "Furnishing": "Fully Furnished", "Rent Type": "Monthly", "Min Duration (months)": 12, "Link": "https://speedhome.com/details/sky-awani-3-kuala-lumpur-lqdumugt"}, {"Title": "Nexus, Kajang", "Property / Area": "Nexus, Kajang", "Room Type": "3BR", "Bedrooms": 3, "Bathrooms": 2, "Price / month (RM)": 1600.0, "Price / year (RM)": 19200.0, "Size (sqft)": 850, "Furnishing": "Partially Furnished", "Rent Type": "Monthly", "Min Duration (months)": 12, "Link": "https://speedhome.com/details/nexus-kajang-pwobjhja"}, {"Title": "Henna Residences, Wangsa Maju", "Property / Area": "Henna Residences, Wangsa Maju", "Room Type": "1BR", "Bedrooms": 1, "Bathrooms": 1, "Price / month (RM)": 1700.0, "Price / year (RM)": 20400.0, "Size (sqft)": 657, "Furnishing": "Partially Furnished", "Rent Type": "Monthly", "Min Duration (months)": 12, "Link": "https://speedhome.com/details/henna-residences-wangsa-maju-mqssofww"}, {"Title": "Duta Park Residences, Kuala Lumpur", "Property / Area": "Duta Park Residences, Kuala Lumpur", "Room Type": "2BR", "Bedrooms": 2, "Bathrooms": 2, "Price / month (RM)": 2700.0, "Price / year (RM)": 32400.0, "Size (sqft)": 957, "Furnishing": "Partially Furnished", "Rent Type": "Monthly", "Min Duration (months)": 12, "Link": "https://speedhome.com/details/duta-park-residences-kuala-lumpur-jmwynsar"}, {"Title": "Core Residences, TRX", "Property / Area": "Core Residences, TRX", "Room Type": "2BR", "Bedrooms": 2, "Bathrooms": 2, "Price / month (RM)": 5000.0, "Price / year (RM)": 60000.0, "Size (sqft)": 818, "Furnishing": "Fully Furnished", "Rent Type": "Monthly", "Min Duration (months)": 12, "Link": "https://speedhome.com/details/core-residences-trx-cmkbhdjw"}, {"Title": "Tuan 2egacy, Kuala Lumpur", "Property / Area": "Tuan 2egacy, Kuala Lumpur", "Room Type": "3BR", "Bedrooms": 3, "Bathrooms": 2, "Price / month (RM)": 2200.0, "Price / year (RM)": 26400.0, "Size (sqft)": 872, "Furnishing": "Fully Furnished", "Rent Type": "Monthly", "Min Duration (months)": 12, "Link": "https://speedhome.com/details/tuan-2egacy-kuala-lumpur-knkgvznx"}, {"Title": "Residensi Rimbunan Perkasa, D'Vine by Exsim", "Property / Area": "Residensi Rimbunan Perkasa, D'Vine by Exsim", "Room Type": "2BR", "Bedrooms": 2, "Bathrooms": 1, "Price / month (RM)": 1600.0, "Price / year (RM)": 19200.0, "Size (sqft)": 550, "Furnishing": "Fully Furnished", "Rent Type": "Monthly", "Min Duration (months)": 12, "Link": "https://speedhome.com/details/residensi-rimbunan-perkasa-dvine-by-exsim-nefscipr"}, {"Title": "M Vertica, Kuala Lumpur", "Property / Area": "M Vertica, Kuala Lumpur", "Room Type": "3BR", "Bedrooms": 3, "Bathrooms": 2, "Price / month (RM)": 2850.0, "Price / year (RM)": 34200.0, "Size (sqft)": 850, "Furnishing": "Fully Furnished", "Rent Type": "Monthly", "Min Duration (months)": 12, "Link": "https://speedhome.com/details/m-vertica-kuala-lumpur-gmntcxjv"}, {"Title": "The Pano, Kuala Lumpur", "Property / Area": "The Pano, Kuala Lumpur", "Room Type": "3BR", "Bedrooms": 3, "Bathrooms": 2, "Price / month (RM)": 2900.0, "Price / year (RM)": 34800.0, "Size (sqft)": 983, "Furnishing": "Fully Furnished", "Rent Type": "Monthly", "Min Duration (months)": 6, "Link": "https://speedhome.com/details/the-pano-kuala-lumpur-yfmicyed"}, {"Title": "D Residence, Block D", "Property / Area": "D Residence, Block D", "Room Type": "3BR", "Bedrooms": 3, "Bathrooms": 3, "Price / month (RM)": 2000.0, "Price / year (RM)": 24000.0, "Size (sqft)": 1460, "Furnishing": "Fully Furnished", "Rent Type": "Monthly", "Min Duration (months)": 12, "Link": "https://speedhome.com/details/d-residence-block-d-xiamyntf"}, {"Title": "Meta Residences, Seri Kembangan", "Property / Area": "Meta Residences, Seri Kembangan", "Room Type": "3BR", "Bedrooms": 3, "Bathrooms": 2, "Price / month (RM)": 2300.0, "Price / year (RM)": 27600.0, "Size (sqft)": 700, "Furnishing": "Fully Furnished", "Rent Type": "Monthly", "Min Duration (months)": 12, "Link": "https://speedhome.com/details/meta-residences-seri-kembangan-pgvhhclo"}, {"Title": "Maya Bay Residences, Banting", "Property / Area": "Maya Bay Residences, Banting", "Room Type": "3BR", "Bedrooms": 3, "Bathrooms": 2, "Price / month (RM)": 1800.0, "Price / year (RM)": 21600.0, "Size (sqft)": 815, "Furnishing": "Partially Furnished", "Rent Type": "Monthly", "Min Duration (months)": 12, "Link": "https://speedhome.com/details/maya-bay-residences-banting-yrjzuvfs"}, {"Title": "Residensi Bidoria, Bidor", "Property / Area": "Residensi Bidoria, Bidor", "Room Type": "3BR", "Bedrooms": 3, "Bathrooms": 2, "Price / month (RM)": 680.0, "Price / year (RM)": 8160.0, "Size (sqft)": 1400, "Furnishing": "Unfurnished", "Rent Type": "Monthly", "Min Duration (months)": 12, "Link": "https://speedhome.com/details/residensi-bidoria-bidor-hjnnmwtg"}, {"Title": "Seasons Garden Residences, Kuala Lumpur", "Property / Area": "Seasons Garden Residences, Kuala Lumpur", "Room Type": "3BR", "Bedrooms": 3, "Bathrooms": 2, "Price / month (RM)": 1800.0, "Price / year (RM)": 21600.0, "Size (sqft)": 770, "Furnishing": "Fully Furnished", "Rent Type": "Monthly", "Min Duration (months)": 12, "Link": "https://speedhome.com/details/seasons-garden-residences-kuala-lumpur-mnyjdkuw"}, {"Title": "Maya Bay Residences, Banting", "Property / Area": "Maya Bay Residences, Banting", "Room Type": "3BR", "Bedrooms": 3, "Bathrooms": 2, "Price / month (RM)": 2000.0, "Price / year (RM)": 24000.0, "Size (sqft)": 818, "Furnishing": "Fully Furnished", "Rent Type": "Monthly", "Min Duration (months)": 12, "Link": "https://speedhome.com/details/maya-bay-residences-banting-cdebdohz"}, {"Title": "Flora Residency, Setapak", "Property / Area": "Flora Residency, Setapak", "Room Type": "3BR", "Bedrooms": 3, "Bathrooms": 2, "Price / month (RM)": 1800.0, "Price / year (RM)": 21600.0, "Size (sqft)": 801, "Furnishing": "Fully Furnished", "Rent Type": "Monthly", "Min Duration (months)": 12, "Link": "https://speedhome.com/details/flora-residency-setapak-rieprpqk"}, {"Title": "Puri Aiyu, Shah Alam", "Property / Area": "Puri Aiyu, Shah Alam", "Room Type": "3BR", "Bedrooms": 3, "Bathrooms": 2, "Price / month (RM)": 1700.0, "Price / year (RM)": 20400.0, "Size (sqft)": 1018, "Furnishing": "Fully Furnished", "Rent Type": "Monthly", "Min Duration (months)": 12, "Link": "https://speedhome.com/details/puri-aiyu-shah-alam-ieobqqhe"}, {"Title": "Duta Park Residences, Kuala Lumpur", "Property / Area": "Duta Park Residences, Kuala Lumpur", "Room Type": "2BR", "Bedrooms": 2, "Bathrooms": 2, "Price / month (RM)": 3000.0, "Price / year (RM)": 36000.0, "Size (sqft)": 957, "Furnishing": "Fully Furnished", "Rent Type": "Monthly", "Min Duration (months)": 12, "Link": "https://speedhome.com/details/duta-park-residences-kuala-lumpur-svvgcomi"}, {"Title": "Razak City Residences, Kuala Lumpur", "Property / Area": "Razak City Residences, Kuala Lumpur", "Room Type": "2BR", "Bedrooms": 2, "Bathrooms": 2, "Price / month (RM)": 1500.0, "Price / year (RM)": 18000.0, "Size (sqft)": 800, "Furnishing": "Partially Furnished", "Rent Type": "Monthly", "Min Duration (months)": 12, "Link": "https://speedhome.com/details/razak-city-residences-kuala-lumpur-uhudaazn"}, {"Title": "Ariza Garden Villa, Batu Caves", "Property / Area": "Ariza Garden Villa, Batu Caves", "Room Type": "3BR", "Bedrooms": 3, "Bathrooms": 3, "Price / month (RM)": 2200.0, "Price / year (RM)": 26400.0, "Size (sqft)": 1300, "Furnishing": "Partially Furnished", "Rent Type": "Monthly", "Min Duration (months)": 12, "Link": "https://speedhome.com/details/ariza-garden-villa-batu-caves-bvoedjcu"}, {"Title": "Lavender Residences, Kajang", "Property / Area": "Lavender Residences, Kajang", "Room Type": "3BR", "Bedrooms": 3, "Bathrooms": 2, "Price / month (RM)": 2300.0, "Price / year (RM)": 27600.0, "Size (sqft)": 1080, "Furnishing": "Partially Furnished", "Rent Type": "Monthly", "Min Duration (months)": 12, "Link": "https://speedhome.com/details/lavender-residences-kajang-asxjfpnu"}, {"Title": "Acacia Residences, Sepang", "Property / Area": "Acacia Residences, Sepang", "Room Type": "Room", "Bedrooms": 1, "Bathrooms": 1, "Price / month (RM)": 715.0, "Price / year (RM)": 8580.0, "Size (sqft)": null, "Furnishing": "Fully Furnished", "Rent Type": "Monthly", "Min Duration (months)": 6, "Link": "https://speedhome.com/details/acacia-residences-sepang-bfaipqsp"}, {"Title": "Henna Residences, Wangsa Maju", "Property / Area": "Henna Residences, Wangsa Maju", "Room Type": "2BR", "Bedrooms": 2, "Bathrooms": 2, "Price / month (RM)": 2500.0, "Price / year (RM)": 30000.0, "Size (sqft)": 850, "Furnishing": "Fully Furnished", "Rent Type": "Monthly", "Min Duration (months)": 12, "Link": "https://speedhome.com/details/henna-residences-wangsa-maju-vyxzowai"}, {"Title": "121 Residences, Petaling Jaya", "Property / Area": "121 Residences, Petaling Jaya", "Room Type": "3BR", "Bedrooms": 3, "Bathrooms": 2, "Price / month (RM)": 3300.0, "Price / year (RM)": 39600.0, "Size (sqft)": 750, "Furnishing": "Partially Furnished", "Rent Type": "Monthly", "Min Duration (months)": 12, "Link": "https://speedhome.com/details/121-residences-petaling-jaya-hpvfnght"}]}